{
    " haiti": 40030,
    " united kingdom": 142890,
    " suriname": 4270,
    " lebanon": 40061,
    " trinidad and tobago": 7819,
    " thailand": 231933,
    " kazakhstan": 17557,
    " north macedonia": 822,
    " argentina": 81507,
    " myanmar": 46664,
    " ireland": 282044,
    " slovenia": 34780,
    " serbia": 37019,
    " iraq": 80385,
    " lesotho": 3935,
    " netherlands": 120410,
    " portugal": 129046,
    " brazil": 348255,
    " south korea": 86166,
    " cuba": 131197,
    " malta": 38466,
    " bangladesh": 67023,
    " saudi arabia": 36243,
    " guyana": 9758,
    " nigeria": 124116,
    " kuwait": 22375,
    " denmark": 58549,
    " kosovo": 7434,
    " dominica": 39233,
    " qatar": 53770,
    " mozambique": 13812,
    " israel": 222512,
    " guatemala": 36623,
    " vietnam": 182123,
    " paraguay": 7976,
    " nepal": 82925,
    " botswana": 18151,
    " taiwan": 63827,
    " bahrain": 23255,
    " romania": 69453,
    " ecuador": 41079,
    " algeria": 18937,
    " croatia": 95769,
    " brunei": 8850,
    " hungary": 48790,
    " china": 1099019,
    " ethiopia": 59140,
    " new zealand": 225957,
    " switzerland": 122242,
    " canada": 553044,
    " greece": 199170,
    " south africa": 221095,
    " oman": 25261,
    " slovakia": 18076,
    " sweden": 106268,
    " nicaragua": 8447,
    " norway": 107245,
    " belgium": 80464,
    " czechia": 1693,
    " mexico": 354939,
    " senegal": 17713,
    " cyprus": 48815,
    " chile": 98184,
    " malaysia": 124639,
    " latvia": 19240,
    " mongolia": 32423,
    " poland": 98000,
    " kyrgyzstan": 6706,
    " sri lanka": 79292,
    " ghana": 49459,
    " iran": 126153,
    " democratic republic of the congo": 2522,
    " japan": 1060138,
    " france": 740998,
    " italy": 509836,
    " barbados": 27192,
    " singapore": 211803,
    " costa rica": 60820,
    " estonia": 22893,
    " bosnia and herzegovina": 6882,
    " united arab emirates": 32918,
    " panama": 66913,
    " colombia": 85774,
    " austria": 139174,
    " philippines": 131938,
    " côte d'ivoire": 1409,
    " indonesia": 224075,
    " laos": 27548,
    " azerbaijan": 17545,
    " morocco": 65301,
    " finland": 51567,
    " saint lucia": 3667,
    " cambodia": 58986,
    " lithuania": 21951,
    " spain": 400139,
    " georgia": 233817,
    " australia": 814355,
    " tanzania": 38572,
    " uruguay": 19644,
    " united states": 505958,
    " russia": 544225,
    " belarus": 20497,
    " luxembourg": 21376,
    " bolivia": 28764,
    " el salvador": 11338,
    " namibia": 33887,
    " honduras": 17013,
    " egypt": 278911,
    " bulgaria": 49899,
    " india": 1929767,
    " turkey": 321709,
    " ukraine": 105160,
    " germany": 442230,
    " peru": 119976,
    " comoros": 2224
}